auto_group/__init__.py
auto_group/config.py
auto_group/customised_folders.py
auto_group/default_folders.py
auto_group/determine_location.py
auto_group/exceptions.py
auto_group/gather_files.py
auto_group/type_of_file.py
auto_group/winRightClick.py
sortmyfolder-0.0.35.dist-info/LICENCE.txt
sortmyfolder-0.0.35.dist-info/METADATA
sortmyfolder-0.0.35.dist-info/WHEEL
sortmyfolder-0.0.35.dist-info/entry_points.txt
sortmyfolder-0.0.35.dist-info/top_level.txt
sortmyfolder-0.0.35.dist-info/RECORD
