Metadata-Version: 2.1
Name: sortmyfolder
Version: 0.0.35
Summary: Auto sorting tool to allow you organise any file or folder in a directory using the file extensions
Author: Emmanuel Agyapong
Author-email: emmanuelagyapong070@gmail.com
Classifier: Programming Language :: Python :: 3
Classifier: License :: OSI Approved :: MIT License
Classifier: Operating System :: OS Independent
Requires-Python: >=3.7
License-File: LICENCE.txt
